pyvent/__init__.py
pyvent/client.py
pyvent/node.py
pyvent/server.py
pyvent/utils.py
pyvent-0.1.1.dist-info/DESCRIPTION.rst
pyvent-0.1.1.dist-info/METADATA
pyvent-0.1.1.dist-info/RECORD
pyvent-0.1.1.dist-info/WHEEL
pyvent-0.1.1.dist-info/metadata.json
pyvent-0.1.1.dist-info/top_level.txt
