Metadata-Version: 2.0
Name: pyvent
Version: 0.1.1
Summary: IPC over ZMQ, made easy
Home-page: https://github.com/aprowe/pyvent
Author: Alexander Rowe
Author-email: alexrowe707@gmail.com
License: MIT
Platform: UNKNOWN
Requires-Python: >=3.6.0
Requires-Dist: PyDispatcher
Requires-Dist: pyzmq
